qmb/__init__.py
qmb/__main__.py
qmb/_hamiltonian.cpp
qmb/_hamiltonian_cpu.cpp
qmb/_hamiltonian_cuda.cu
qmb/_version.py
qmb/attention.py
qmb/bitspack.py
qmb/chop_imag.py
qmb/common.py
qmb/crossmlp.py
qmb/fcidump.py
qmb/haar.py
qmb/hamiltonian.py
qmb/hubbard.py
qmb/ising.py
qmb/list_loss.py
qmb/losses.py
qmb/mlp.py
qmb/model_dict.py
qmb/openfermion.py
qmb/optimizer.py
qmb/pert.py
qmb/precompile.py
qmb/random_engine.py
qmb/rldiag.py
qmb/run.py
qmb/subcommand_dict.py
qmb/version.py
qmb/vmc.py
qmb-0.0.52.dist-info/licenses/LICENSE.md
qmb-0.0.52.dist-info/METADATA
qmb-0.0.52.dist-info/WHEEL
qmb-0.0.52.dist-info/entry_points.txt
qmb-0.0.52.dist-info/top_level.txt
qmb-0.0.52.dist-info/RECORD
