Metadata-Version: 2.4
Name: qmb
Version: 0.0.52
Summary: Quantum Manybody Problem
Author-email: Hao Zhang <hzhangxyz@outlook.com>
License-Expression: GPL-3.0-or-later
Project-URL: Homepage, https://github.com/USTC-KnowledgeComputingLab/qmb
Project-URL: Documentation, https://github.com/USTC-KnowledgeComputingLab/qmb
Project-URL: Repository, https://github.com/USTC-KnowledgeComputingLab/qmb.git
Project-URL: Issues, https://github.com/USTC-KnowledgeComputingLab/qmb/issues
Keywords: quantum,manybody,quantum-chemistry,quantum-simulation,molecular-simulation,algorithms,simulation,wave-function,ground-state,ansatz,torch,pytorch
Classifier: Development Status :: 4 - Beta
Classifier: Environment :: Console
Classifier: Programming Language :: C++
Classifier: Programming Language :: Python :: 3
Classifier: Environment :: GPU :: NVIDIA CUDA
Classifier: Topic :: Scientific/Engineering :: Mathematics
Classifier: Topic :: Scientific/Engineering :: Physics
Classifier: Topic :: Scientific/Engineering :: Chemistry
Classifier: Topic :: Software Development :: Libraries :: Python Modules
Requires-Python: >=3.12
License-File: LICENSE.md
Requires-Dist: platformdirs~=4.3.7
Requires-Dist: numpy<2.4.0,>=1.26.4
Requires-Dist: scipy<1.17.0,>=1.15.2
Requires-Dist: torch<2.9,>=2.6
Requires-Dist: pybind11<3.1.0,>=2.13.6
Requires-Dist: ninja<1.13.1.0,>=1.11.1.4
Requires-Dist: tyro~=0.9.18
Requires-Dist: pyyaml~=6.0.2
Requires-Dist: openfermion~=1.7.0
Requires-Dist: tensorboard<2.21,>=2.19
Requires-Dist: standard-imghdr~=3.13.0; python_version >= "3.13"
Provides-Extra: dev
Requires-Dist: yapf~=0.43.0; extra == "dev"
Requires-Dist: pylint~=3.3.6; extra == "dev"
Requires-Dist: mypy<1.18,>=1.15; extra == "dev"
Requires-Dist: pytest<8.5.0,>=8.3.5; extra == "dev"
Requires-Dist: pytest-cov<6.3,>=6.0; extra == "dev"
Requires-Dist: types-pyyaml~=6.0.12.20250326; extra == "dev"
Dynamic: license-file
